reachcollective/__init__.py
reachcollective/datagrid/__init__.py
reachcollective/datagrid/datagrid.py
reachcollective/datagrid/filters.py
reachcollective/datagrid/paginator.py
reachcollective/datagrid/query_builder.py
reachcollective/datagrid/query_params.py
reachcollective/datagrid/schemas.py
reachcollective/repositories/__init__.py
reachcollective/repositories/base.py
reachcollective/repositories/schemas.py
reachcollective/services/__init__.py
reachcollective/services/base.py
reachcollective/utils/__init__.py
reachcollective/utils/core.py
reachcollective/utils/exception.py
reachcollective/utils/log/__init__.py
reachcollective/utils/log/aws.py
reachcollective/utils/log/db.py
reachcollective/utils/log/gcp.py
reachcollective/utils/log/log.py
reachcollective/utils/log/schemas.py
reachcollective/utils/render.py
reachcollective_utils-0.1.30.dist-info/METADATA
reachcollective_utils-0.1.30.dist-info/WHEEL
reachcollective_utils-0.1.30.dist-info/RECORD
