Metadata-Version: 2.4
Name: reachcollective-utils
Version: 0.1.30
Summary: Utilities for developing RESTful API, Open API projects with FastAPI and Python
Author: Juan Minaya
Author-email: minayaleon@gmail.com
Requires-Python: >=3.12
Classifier: License :: OSI Approved :: MIT License
Requires-Dist: fastapi[standard] (>=0.120.0,<0.125.0)
Requires-Dist: sqlmodel (>=0.0.27,<0.0.28)
